tpljson/__init__.py
tpljson/exceptions.py
tpljson/json.py
tpljson/template.py
tpljson/text.py
tpljson-0.1.5.dist-info/LICENSE
tpljson-0.1.5.dist-info/METADATA
tpljson-0.1.5.dist-info/WHEEL
tpljson-0.1.5.dist-info/top_level.txt
tpljson-0.1.5.dist-info/RECORD
