Metadata-Version: 2.1
Name: tpljson
Version: 0.1.5
Summary: json compatible library supporting templating
Home-page: https://github.com/OpenBigDataPlatform/tpljson
Author: OpenBigDataPlatform
Author-email: 
License: MIT License
Keywords: json template
Platform: UNKNOWN
Classifier: Programming Language :: Python
Classifier: Development Status :: 4 - Beta
Classifier: Operating System :: OS Independent
Classifier: Intended Audience :: Developers
Classifier: Topic :: Software Development :: Libraries :: Python Modules
Classifier: Programming Language :: Python :: 3 :: Only
Classifier: Programming Language :: Python :: 3.6
Classifier: Programming Language :: Python :: 3.7
Classifier: Programming Language :: Python :: 3.8
Classifier: Programming Language :: Python :: 3.9
Requires-Python: >=3.6
Requires-Dist: objectpath (==0.6.1)
Requires-Dist: colorama (==0.4.4)
Requires-Dist: commentjson (==0.9.0)
Requires-Dist: lark-parser (==0.7.8)
